{
  "job_id": "10822809",
  "company_name": "Precisely",
  "title": "Software Engineering Intern",
  "description": "Precisely is the leader in data integrity. We empower businesses to make more confident decisions based on trusted data through a unique combination of software, data enrichment products and strategic services. What does this mean to you? For starters, it means joining a company focused on delivering outstanding innovation and support that helps customers increase revenue, lower costs and reduce risk. In fact, Precisely powers better decisions for more than 12,000 global organizations, including 95 of the Fortune 100. Precisely's 2500 employees are unified by four company core values that are central to who we are and how we operate: Openness, Determination, Individuality, and Collaboration. We are committed to career development for our employees and offer opportunities for growth, learning and building community. With a \"work from anywhere\" culture, we celebrate diversity in a distributed environment with a presence in 30 countries as well as 20 offices in over 5 continents. Learn more about why it's an exciting time to join Precisely!\nThis position is 100% remote anywhere in the US\nOverview:\nPrecisely’s Summer Internship Program is a paid, part-time opportunity for undergraduate students actively enrolled in university. This is an 10-week program that begins Monday June 8, 2026 and ends Friday August 14, 2026. This opportunity is 100% remote and you must be located in the United States during the summer internship. The Software Engineering Intern will work closely with the R&D team.\nThe intern will assist with building and validating data pipelines and enabling engineering metrics dashboards in Tableau to improve visibility into engineering performance. As a capstone or side project, the intern will design and build a small custom application or prototype using curated engineering datasets. Key deliverables include functional data integrations, documented metrics definitions, updated dashboards, and a completed prototype demonstrating applied learning.\nWhat you will do:\nYou will assist in integrating and validating data from engineering systems such as Jellyfish, Jira, GitLab, and GitHub to support engineering metrics reporting.\nYou will work with us to help build, test, and refine data pipelines that enable reliable and consistent engineering metrics.\nYou will support the development and maintenance of Tableau dashboards that provide visibility into engineering performance and trends.\nYou will help document metrics definitions, data sources, and reporting processes so they are easy for teams to understand and reuse.\nYou will collaborate with engineers and analysts to gather basic reporting requirements and clarify data needs.\nYou will investigate and help resolve basic data quality or reporting issues with guidance from your mentor.\nYou will design and build a small custom application or prototype using engineering datasets as a side project.\nYou will share progress, learnings, and outcomes with the team through regular checkins and a final presentation.\nWhat we are looking for:\nEntry programming experience in Python and/or Node.js, gained through coursework, academic projects, or internships\nIntroductory experience working with REST APIs, including making requests and handling JSON responses\nFamiliarity with version control concepts and tools such as GitHub or GitLab (class or personal use acceptable)\nBasic understanding of data concepts, including reading, cleaning, and validating datasets\nExposure to analytics or visualization tools (such as Tableau, Excel, or similar), or a strong interest in learning them\nAbility to gather basic requirements by asking questions and incorporating feedback from teammates\nStrong written and verbal communication skills, including the ability to document work clearly\nCuriosity, willingness to learn new tools and systems, and comfort working with guidance in a collaborative environment\nProgram benefits:\nValuable experience related to the degree you are pursuing.\nHands on experience at an established tech company.\nNetworking opportunities with company leaders around the globe.",
  "max_salary": 25,
  "pay_period": "HOURLY",
  "location": "Remote",
  "company_id": null,
  "views": null,
  "med_salary": 25,
  "job_posting_url": "https://app.joinhandshake.com/jobs/10822809",
  "original_listed_time": 1774340005,
  "expiry": 1776932005
}